[
  {
    "algorithm": "ppo",
    "model": "ppo_scaleinv_best.pt",
    "instance": "6x6_6x6x2",
    "makespan": 2662,
    "reward": -32.540270119591554,
    "decisions": 271,
    "tasks": 36,
    "force_rest_time": 368,
    "invalid_actions": 0,
    "mean_task_fatigue": 0.8701041539025921,
    "max_task_fatigue": 0.9976995937205299
  },
  {
    "algorithm": "ppo",
    "model": "ppo_scaleinv_best.pt",
    "instance": "10x5_10x5x3",
    "makespan": 3161,
    "reward": -41.45695092129345,
    "decisions": 512,
    "tasks": 50,
    "force_rest_time": 543,
    "invalid_actions": 0,
    "mean_task_fatigue": 0.8667427757652737,
    "max_task_fatigue": 0.9727817155097038
  },
  {
    "algorithm": "ppo",
    "model": "ppo_scaleinv_best.pt",
    "instance": "15x5_15x5x2",
    "makespan": 4695,
    "reward": -63.086255260815804,
    "decisions": 706,
    "tasks": 75,
    "force_rest_time": 837,
    "invalid_actions": 0,
    "mean_task_fatigue": 0.8729573893457805,
    "max_task_fatigue": 0.977520426908551
  },
  {
    "algorithm": "ppo",
    "model": "ppo_scaleinv_best.pt",
    "instance": "10x10_10x10x4",
    "makespan": 3841,
    "reward": -42.263684333970424,
    "decisions": 548,
    "tasks": 100,
    "force_rest_time": 1052,
    "invalid_actions": 0,
    "mean_task_fatigue": 0.8637642789068006,
    "max_task_fatigue": 0.9913954784726747
  },
  {
    "algorithm": "ppo",
    "model": "ppo_scaleinv_best.pt",
    "instance": "15x10_15x10x3",
    "makespan": 6103,
    "reward": -65.32977789247848,
    "decisions": 814,
    "tasks": 150,
    "force_rest_time": 1667,
    "invalid_actions": 0,
    "mean_task_fatigue": 0.8714399233632661,
    "max_task_fatigue": 0.9868262371481503
  },
  {
    "algorithm": "ppo",
    "model": "ppo_scaleinv_best.pt",
    "instance": "20x10_20x10x5",
    "makespan": 6360,
    "reward": -80.10382109172987,
    "decisions": 1247,
    "tasks": 200,
    "force_rest_time": 2109,
    "invalid_actions": 0,
    "mean_task_fatigue": 0.8596843630222856,
    "max_task_fatigue": 0.9965047608147009
  },
  {
    "algorithm": "ppo",
    "model": "ppo_scaleinv_best.pt",
    "instance": "30x10_30x10x2",
    "makespan": 17802,
    "reward": -123.22759660068184,
    "decisions": 1647,
    "tasks": 300,
    "force_rest_time": 3527,
    "invalid_actions": 0,
    "mean_task_fatigue": 0.8851431358939974,
    "max_task_fatigue": 0.9941799739317101
  },
  {
    "algorithm": "ppo",
    "model": "ppo_scaleinv_best.pt",
    "instance": "30x10_30x10x6",
    "makespan": 8580,
    "reward": -106.550486924382,
    "decisions": 1732,
    "tasks": 300,
    "force_rest_time": 3193,
    "invalid_actions": 0,
    "mean_task_fatigue": 0.8659766027351551,
    "max_task_fatigue": 0.9965285792884064
  },
  {
    "algorithm": "ppo",
    "model": "ppo_scaleinv_best.pt",
    "instance": "50x10_50x10x3",
    "makespan": 21528,
    "reward": -174.95583441688575,
    "decisions": 2603,
    "tasks": 500,
    "force_rest_time": 5929,
    "invalid_actions": 0,
    "mean_task_fatigue": 0.8854350559585272,
    "max_task_fatigue": 0.997545166207652
  },
  {
    "algorithm": "ppo",
    "model": "ppo_scaleinv_best.pt",
    "instance": "100x10_100x10x3",
    "makespan": 42276,
    "reward": -343.34882204778035,
    "decisions": 5303,
    "tasks": 1000,
    "force_rest_time": 11451,
    "invalid_actions": 0,
    "mean_task_fatigue": 0.8808858384991113,
    "max_task_fatigue": 0.9969622752731832
  }
]